{
  "products": [
    {
      "id": 1,
      "name": "Product 1",
      "price": 100,
      "description": "Description for Product 1",
      "discount": 10,
      "imageUrl": "https://images.stockcake.com/public/b/5/2/b52d5e03-9e43-412d-99ae-675c1e61db56/executive-presenting-product-stockcake.jpg"
    },
    {
      "id": 2,
      "name": "Product 2",
      "price": 200,
      "description": "Description for Product 2",
      "discount": 0,
      "imageUrl": "https://images.stockcake.com/public/5/6/9/569e7609-497a-4e44-a1d4-5a8d6270609c/coconut-beauty-product-stockcake.jpg"
    },
    {
      "id": 3,
      "name": "Product 3",
      "price": 150,
      "description": "Lorem ipsum dolor sit amet consectetur adipisicing elit. Ipsa, laboriosam voluptates ad id nostrum suscipit repellat hic, voluptatem blanditiis nisi expedita! Quisquam earum deserunt sapiente doloremque dolor quidem quis accusantium! Lorem ipsum dolor sit amet consectetur adipisicing elit. Ipsa, laboriosam voluptates ad id nostrum suscipit repellat hic, voluptatem blanditiis nisi expedita! Quisquam earum deserunt sapiente doloremque dolor quidem quis accusantium!",
      "discount": 5,
      "imageUrl": "https://images.stockcake.com/public/5/6/9/569e7609-497a-4e44-a1d4-5a8d6270609c/coconut-beauty-product-stockcake.jpg"
    },
    {
      "id": 4,
      "name": "Product 4",
      "price": 300,
      "description": "Description for Product 4",
      "discount": 60,
      "imageUrl": "https://images.stockcake.com/public/b/5/2/b52d5e03-9e43-412d-99ae-675c1e61db56/executive-presenting-product-stockcake.jpg"
    }
  ]
}
